Compiled from "SourceFile"
class com.adjust.sdk.sig.NativeLibHelper implements com.adjust.sdk.sig.a {
  public com.adjust.sdk.sig.NativeLibHelper();
    descriptor: ()V
    Code:
       0: aload_0
       1: invokespecial #13                 // Method java/lang/Object."<init>":()V
       4: return

  private native byte[] nSign(android.content.Context, java.lang.Object, byte[], int);
    descriptor: (Landroid/content/Context;Ljava/lang/Object;[BI)[B

  private native void nOnResume();
    descriptor: ()V

  static {};
    descriptor: ()V
    Code:
       0: ldc           #19                 // String signer
       2: invokestatic  #25                 // Method java/lang/System.loadLibrary:(Ljava/lang/String;)V
       5: goto          36
       8: astore_0
       9: new           #29                 // class java/lang/StringBuilder
      12: dup
      13: aload_0
      14: swap
      15: ldc           #31                 // String Signer Library could not be loaded:
      17: invokespecial #33                 // Method java/lang/StringBuilder."<init>":(Ljava/lang/String;)V
      20: invokevirtual #39                 // Method java/lang/Throwable.getMessage:()Ljava/lang/String;
      23: invokevirtual #43                 // Method java/lang/StringBuilder.append:(Ljava/lang/String;)Ljava/lang/StringBuilder;
      26: invokevirtual #46                 // Method java/lang/StringBuilder.toString:()Ljava/lang/String;
      29: ldc           #48                 // String NativeLibHelper
      31: swap
      32: invokestatic  #54                 // Method android/util/Log.e:(Ljava/lang/String;Ljava/lang/String;)I
      35: pop
      36: return
    Exception table:
       from    to  target type
           0     8     8   Class java/lang/UnsatisfiedLinkError

  public final byte[] a(android.content.Context, java.lang.Object, byte[], int);
    descriptor: (Landroid/content/Context;Ljava/lang/Object;[BI)[B
    Code:
       0: aload_0
       1: aload_1
       2: aload_2
       3: aload_3
       4: iload         4
       6: invokespecial #57                 // Method nSign:(Landroid/content/Context;Ljava/lang/Object;[BI)[B
       9: areturn

  public final void a();
    descriptor: ()V
    Code:
       0: aload_0
       1: invokespecial #59                 // Method nOnResume:()V
       4: return
}
Compiled from "SourceFile"
public class com.adjust.sdk.sig.Signer {
  public boolean a;
    descriptor: Z

  public com.adjust.sdk.sig.d b;
    descriptor: Lcom/adjust/sdk/sig/d;

  public com.adjust.sdk.sig.a c;
    descriptor: Lcom/adjust/sdk/sig/a;

  public com.adjust.sdk.sig.c d;
    descriptor: Lcom/adjust/sdk/sig/c;

  public com.adjust.sdk.sig.Signer();
    descriptor: ()V
    Code:
       0: aload_0
       1: dup
       2: invokespecial #19                 // Method java/lang/Object."<init>":()V
       5: iconst_0
       6: putfield      #21                 // Field a:Z
       9: return

  public static java.lang.String getVersion();
    descriptor: ()Ljava/lang/String;
    Code:
       0: ldc           #25                 // String 3.67.0
       2: areturn

  public synchronized void onResume();
    descriptor: ()V
    Code:
       0: aload_0
       1: dup
       2: invokevirtual #28                 // Method a:()V
       5: getfield      #30                 // Field b:Lcom/adjust/sdk/sig/d;
       8: aload_0
       9: getfield      #32                 // Field c:Lcom/adjust/sdk/sig/a;
      12: astore_0
      13: invokevirtual #36                 // Method java/lang/Object.getClass:()Ljava/lang/Class;
      16: pop
      17: getstatic     #39                 // Field com/adjust/sdk/sig/d.a:Z
      20: ifeq          26
      23: goto          33
      26: aload_0
      27: checkcast     #43                 // class com/adjust/sdk/sig/NativeLibHelper
      30: invokevirtual #44                 // Method com/adjust/sdk/sig/NativeLibHelper.a:()V
      33: return

  public synchronized void sign(android.content.Context, java.util.Map<java.lang.String, java.lang.String>, java.lang.String, java.lang.String);
    descriptor: (Landroid/content/Context;Ljava/util/Map;Ljava/lang/String;Ljava/lang/String;)V
    Code:
       0: aload_1
       1: aload_0
       2: dup
       3: invokevirtual #28                 // Method a:()V
       6: getfield      #30                 // Field b:Lcom/adjust/sdk/sig/d;
       9: aload_0
      10: dup
      11: getfield      #49                 // Field d:Lcom/adjust/sdk/sig/c;
      14: astore_0
      15: getfield      #32                 // Field c:Lcom/adjust/sdk/sig/a;
      18: astore_1
      19: invokevirtual #36                 // Method java/lang/Object.getClass:()Ljava/lang/Class;
      22: pop
      23: aload_0
      24: aload_1
      25: aload_2
      26: aload_3
      27: aload         4
      29: invokestatic  #52                 // Method com/adjust/sdk/sig/d.a:(Landroid/content/Context;Lcom/adjust/sdk/sig/c;Lcom/adjust/sdk/sig/a;Ljava/util/Map;Ljava/lang/String;Ljava/lang/String;)V
      32: return

  public synchronized void sign(android.content.Context, java.util.Map<java.lang.String, java.lang.String>, java.util.Map<java.lang.String, java.lang.String>, java.util.Map<java.lang.String, java.lang.String>);
    descriptor: (Landroid/content/Context;Ljava/util/Map;Ljava/util/Map;Ljava/util/Map;)V
    Code:
       0: aload_2
       1: aload_0
       2: dup
       3: invokevirtual #28                 // Method a:()V
       6: getfield      #30                 // Field b:Lcom/adjust/sdk/sig/d;
       9: aload_0
      10: dup
      11: getfield      #49                 // Field d:Lcom/adjust/sdk/sig/c;
      14: astore_0
      15: getfield      #32                 // Field c:Lcom/adjust/sdk/sig/a;
      18: astore        5
      20: invokevirtual #36                 // Method java/lang/Object.getClass:()Ljava/lang/Class;
      23: pop
      24: ifnull        635
      27: aload_2
      28: invokeinterface #60,  1           // InterfaceMethod java/util/Map.isEmpty:()Z
      33: ifne          635
      36: aload_3
      37: ifnull        635
      40: aload         4
      42: ifnonnull     48
      45: goto          635
      48: aload_2
      49: new           #66                 // class java/text/SimpleDateFormat
      52: dup
      53: astore        6
      55: getstatic     #72                 // Field java/util/Locale.US:Ljava/util/Locale;
      58: ldc           #74                 // String yyyy-MM-dd\'T\'HH:mm:ss.SSSZ
      60: swap
      61: invokespecial #77                 // Method java/text/SimpleDateFormat."<init>":(Ljava/lang/String;Ljava/util/Locale;)V
      64: ldc           #79                 // String environment
      66: invokeinterface #83,  2           // InterfaceMethod java/util/Map.get:(Ljava/lang/Object;)Ljava/lang/Object;
      71: ldc           #85                 // String sandbox
      73: swap
      74: invokevirtual #91                 // Method java/lang/String.equals:(Ljava/lang/Object;)Z
      77: dup
      78: istore        7
      80: ifeq          121
      83: new           #93                 // class java/lang/StringBuilder
      86: dup
      87: aload         6
      89: swap
      90: ldc           #95                 // String SDKv5 Signing all the parameters begin:
      92: invokespecial #98                 // Method java/lang/StringBuilder."<init>":(Ljava/lang/String;)V
      95: new           #100                // class java/util/Date
      98: dup
      99: invokestatic  #106                // Method java/lang/System.currentTimeMillis:()J
     102: invokespecial #109                // Method java/util/Date."<init>":(J)V
     105: invokevirtual #115                // Method java/text/DateFormat.format:(Ljava/util/Date;)Ljava/lang/String;
     108: invokevirtual #119                // Method java/lang/StringBuilder.append:(Ljava/lang/String;)Ljava/lang/StringBuilder;
     111: invokevirtual #122                // Method java/lang/StringBuilder.toString:()Ljava/lang/String;
     114: ldc           #124                // String SignerInstance
     116: swap
     117: invokestatic  #130                // Method android/util/Log.v:(Ljava/lang/String;Ljava/lang/String;)I
     120: pop
     121: aload_3
     122: dup
     123: dup
     124: aload_2
     125: new           #132                // class java/util/HashMap
     128: dup
     129: astore        8
     131: invokespecial #133                // Method java/util/HashMap."<init>":()V
     134: invokeinterface #137,  1          // InterfaceMethod java/util/Map.keySet:()Ljava/util/Set;
     139: aload_2
     140: aload         8
     142: invokestatic  #140                // Method com/adjust/sdk/sig/d.a:(Ljava/util/Set;Ljava/util/Map;Ljava/util/Map;)V
     145: ldc           #142                // String activity_kind
     147: invokeinterface #83,  2           // InterfaceMethod java/util/Map.get:(Ljava/lang/Object;)Ljava/lang/Object;
     152: checkcast     #87                 // class java/lang/String
     155: astore        9
     157: ldc           #144                // String client_sdk
     159: invokeinterface #83,  2           // InterfaceMethod java/util/Map.get:(Ljava/lang/Object;)Ljava/lang/Object;
     164: checkcast     #87                 // class java/lang/String
     167: astore        10
     169: ldc           #145                // String a
     171: invokeinterface #83,  2           // InterfaceMethod java/util/Map.get:(Ljava/lang/Object;)Ljava/lang/Object;
     176: ldc           #146                // String b
     178: swap
     179: invokevirtual #91                 // Method java/lang/String.equals:(Ljava/lang/Object;)Z
     182: ifne          546
     185: aload         8
     187: aload_1
     188: aload_0
     189: aload         5
     191: aload         8
     193: aload         9
     195: aload         10
     197: invokestatic  #52                 // Method com/adjust/sdk/sig/d.a:(Landroid/content/Context;Lcom/adjust/sdk/sig/c;Lcom/adjust/sdk/sig/a;Ljava/util/Map;Ljava/lang/String;Ljava/lang/String;)V
     200: ldc           #148                // String signature
     202: invokevirtual #151                // Method java/util/HashMap.containsKey:(Ljava/lang/Object;)Z
     205: ifeq          535
     208: aload         8
     210: ldc           #153                // String adj_signing_id
     212: invokevirtual #151                // Method java/util/HashMap.containsKey:(Ljava/lang/Object;)Z
     215: ifeq          535
     218: aload         8
     220: ldc           #155                // String headers_id
     222: invokevirtual #151                // Method java/util/HashMap.containsKey:(Ljava/lang/Object;)Z
     225: ifeq          535
     228: aload         8
     230: ldc           #157                // String algorithm
     232: invokevirtual #151                // Method java/util/HashMap.containsKey:(Ljava/lang/Object;)Z
     235: ifeq          535
     238: aload         8
     240: ldc           #159                // String native_version
     242: invokevirtual #151                // Method java/util/HashMap.containsKey:(Ljava/lang/Object;)Z
     245: ifne          251
     248: goto          535
     251: aload         4
     253: aload         8
     255: dup
     256: dup
     257: dup2
     258: ldc           #153                // String adj_signing_id
     260: invokevirtual #160                // Method java/util/HashMap.get:(Ljava/lang/Object;)Ljava/lang/Object;
     263: checkcast     #87                 // class java/lang/String
     266: astore_0
     267: ldc           #155                // String headers_id
     269: invokevirtual #160                // Method java/util/HashMap.get:(Ljava/lang/Object;)Ljava/lang/Object;
     272: checkcast     #87                 // class java/lang/String
     275: astore_1
     276: ldc           #148                // String signature
     278: invokevirtual #160                // Method java/util/HashMap.get:(Ljava/lang/Object;)Ljava/lang/Object;
     281: checkcast     #87                 // class java/lang/String
     284: astore        5
     286: ldc           #157                // String algorithm
     288: invokevirtual #160                // Method java/util/HashMap.get:(Ljava/lang/Object;)Ljava/lang/Object;
     291: checkcast     #87                 // class java/lang/String
     294: astore        8
     296: ldc           #159                // String native_version
     298: invokevirtual #160                // Method java/util/HashMap.get:(Ljava/lang/Object;)Ljava/lang/Object;
     301: checkcast     #87                 // class java/lang/String
     304: astore        9
     306: new           #93                 // class java/lang/StringBuilder
     309: dup
     310: dup2
     311: aload         5
     313: swap
     314: ldc           #162                // String signature=\"
     316: invokespecial #98                 // Method java/lang/StringBuilder."<init>":(Ljava/lang/String;)V
     319: invokevirtual #119                // Method java/lang/StringBuilder.append:(Ljava/lang/String;)Ljava/lang/StringBuilder;
     322: pop
     323: ldc           #164                // String \"
     325: invokevirtual #119                // Method java/lang/StringBuilder.append:(Ljava/lang/String;)Ljava/lang/StringBuilder;
     328: pop
     329: invokevirtual #122                // Method java/lang/StringBuilder.toString:()Ljava/lang/String;
     332: astore        5
     334: new           #93                 // class java/lang/StringBuilder
     337: dup
     338: dup2
     339: aload_0
     340: swap
     341: ldc           #166                // String adj_signing_id=\"
     343: invokespecial #98                 // Method java/lang/StringBuilder."<init>":(Ljava/lang/String;)V
     346: invokevirtual #119                // Method java/lang/StringBuilder.append:(Ljava/lang/String;)Ljava/lang/StringBuilder;
     349: pop
     350: ldc           #164                // String \"
     352: invokevirtual #119                // Method java/lang/StringBuilder.append:(Ljava/lang/String;)Ljava/lang/StringBuilder;
     355: pop
     356: invokevirtual #122                // Method java/lang/StringBuilder.toString:()Ljava/lang/String;
     359: astore_0
     360: new           #93                 // class java/lang/StringBuilder
     363: dup
     364: dup2
     365: aload_1
     366: swap
     367: ldc           #168                // String headers_id=\"
     369: invokespecial #98                 // Method java/lang/StringBuilder."<init>":(Ljava/lang/String;)V
     372: invokevirtual #119                // Method java/lang/StringBuilder.append:(Ljava/lang/String;)Ljava/lang/StringBuilder;
     375: pop
     376: ldc           #164                // String \"
     378: invokevirtual #119                // Method java/lang/StringBuilder.append:(Ljava/lang/String;)Ljava/lang/StringBuilder;
     381: pop
     382: invokevirtual #122                // Method java/lang/StringBuilder.toString:()Ljava/lang/String;
     385: astore_1
     386: new           #93                 // class java/lang/StringBuilder
     389: dup
     390: dup2
     391: aload         8
     393: swap
     394: ldc           #170                // String algorithm=\"
     396: invokespecial #98                 // Method java/lang/StringBuilder."<init>":(Ljava/lang/String;)V
     399: invokevirtual #119                // Method java/lang/StringBuilder.append:(Ljava/lang/String;)Ljava/lang/StringBuilder;
     402: pop
     403: ldc           #164                // String \"
     405: invokevirtual #119                // Method java/lang/StringBuilder.append:(Ljava/lang/String;)Ljava/lang/StringBuilder;
     408: pop
     409: invokevirtual #122                // Method java/lang/StringBuilder.toString:()Ljava/lang/String;
     412: astore        8
     414: new           #93                 // class java/lang/StringBuilder
     417: dup
     418: dup2
     419: aload         9
     421: swap
     422: ldc           #172                // String native_version=\"
     424: invokespecial #98                 // Method java/lang/StringBuilder."<init>":(Ljava/lang/String;)V
     427: invokevirtual #119                // Method java/lang/StringBuilder.append:(Ljava/lang/String;)Ljava/lang/StringBuilder;
     430: pop
     431: ldc           #164                // String \"
     433: invokevirtual #119                // Method java/lang/StringBuilder.append:(Ljava/lang/String;)Ljava/lang/StringBuilder;
     436: pop
     437: invokevirtual #122                // Method java/lang/StringBuilder.toString:()Ljava/lang/String;
     440: astore        9
     442: new           #93                 // class java/lang/StringBuilder
     445: dup
     446: dup
     447: astore        10
     449: aload         9
     451: aload         10
     453: dup
     454: aload_1
     455: aload         10
     457: dup
     458: aload         8
     460: aload         10
     462: dup
     463: aload_0
     464: aload         10
     466: dup
     467: aload         5
     469: aload         10
     471: ldc           #174                // String Signature
     473: invokespecial #98                 // Method java/lang/StringBuilder."<init>":(Ljava/lang/String;)V
     476: invokevirtual #119                // Method java/lang/StringBuilder.append:(Ljava/lang/String;)Ljava/lang/StringBuilder;
     479: pop
     480: ldc           #176                // String ,
     482: invokevirtual #119                // Method java/lang/StringBuilder.append:(Ljava/lang/String;)Ljava/lang/StringBuilder;
     485: pop
     486: invokevirtual #119                // Method java/lang/StringBuilder.append:(Ljava/lang/String;)Ljava/lang/StringBuilder;
     489: pop
     490: ldc           #176                // String ,
     492: invokevirtual #119                // Method java/lang/StringBuilder.append:(Ljava/lang/String;)Ljava/lang/StringBuilder;
     495: pop
     496: invokevirtual #119                // Method java/lang/StringBuilder.append:(Ljava/lang/String;)Ljava/lang/StringBuilder;
     499: pop
     500: ldc           #176                // String ,
     502: invokevirtual #119                // Method java/lang/StringBuilder.append:(Ljava/lang/String;)Ljava/lang/StringBuilder;
     505: pop
     506: invokevirtual #119                // Method java/lang/StringBuilder.append:(Ljava/lang/String;)Ljava/lang/StringBuilder;
     509: pop
     510: ldc           #176                // String ,
     512: invokevirtual #119                // Method java/lang/StringBuilder.append:(Ljava/lang/String;)Ljava/lang/StringBuilder;
     515: pop
     516: invokevirtual #119                // Method java/lang/StringBuilder.append:(Ljava/lang/String;)Ljava/lang/StringBuilder;
     519: pop
     520: invokevirtual #122                // Method java/lang/StringBuilder.toString:()Ljava/lang/String;
     523: ldc           #178                // String authorization
     525: swap
     526: invokeinterface #182,  3          // InterfaceMethod java/util/Map.put:(Ljava/lang/Object;Ljava/lang/Object;)Ljava/lang/Object;
     531: pop
     532: goto          546
     535: ldc           #124                // String SignerInstance
     537: ldc           #184                // String sign: Signature generation failed. Exiting...
     539: invokestatic  #187                // Method android/util/Log.e:(Ljava/lang/String;Ljava/lang/String;)I
     542: pop
     543: goto          643
     546: iload         7
     548: aload_2
     549: invokeinterface #137,  1          // InterfaceMethod java/util/Map.keySet:()Ljava/util/Set;
     554: aload_2
     555: aload         4
     557: invokestatic  #140                // Method com/adjust/sdk/sig/d.a:(Ljava/util/Set;Ljava/util/Map;Ljava/util/Map;)V
     560: new           #189                // class java/util/HashSet
     563: dup
     564: aload_3
     565: swap
     566: iconst_2
     567: anewarray     #87                 // class java/lang/String
     570: dup
     571: dup
     572: iconst_0
     573: ldc           #191                // String network_payload
     575: aastore
     576: iconst_1
     577: ldc           #193                // String endpoint
     579: aastore
     580: invokestatic  #199                // Method java/util/Arrays.asList:([Ljava/lang/Object;)Ljava/util/List;
     583: invokespecial #202                // Method java/util/HashSet."<init>":(Ljava/util/Collection;)V
     586: aload         4
     588: invokestatic  #140                // Method com/adjust/sdk/sig/d.a:(Ljava/util/Set;Ljava/util/Map;Ljava/util/Map;)V
     591: ifeq          643
     594: new           #93                 // class java/lang/StringBuilder
     597: dup
     598: aload         6
     600: swap
     601: ldc           #204                // String SDKv5 Signing all the parameters end  :
     603: invokespecial #98                 // Method java/lang/StringBuilder."<init>":(Ljava/lang/String;)V
     606: new           #100                // class java/util/Date
     609: dup
     610: invokestatic  #106                // Method java/lang/System.currentTimeMillis:()J
     613: invokespecial #109                // Method java/util/Date."<init>":(J)V
     616: invokevirtual #115                // Method java/text/DateFormat.format:(Ljava/util/Date;)Ljava/lang/String;
     619: invokevirtual #119                // Method java/lang/StringBuilder.append:(Ljava/lang/String;)Ljava/lang/StringBuilder;
     622: invokevirtual #122                // Method java/lang/StringBuilder.toString:()Ljava/lang/String;
     625: ldc           #124                // String SignerInstance
     627: swap
     628: invokestatic  #130                // Method android/util/Log.v:(Ljava/lang/String;Ljava/lang/String;)I
     631: pop
     632: goto          643
     635: ldc           #124                // String SignerInstance
     637: ldc           #206                // String sign: One or more parameters are null
     639: invokestatic  #187                // Method android/util/Log.e:(Ljava/lang/String;Ljava/lang/String;)I
     642: pop
     643: return

  public final synchronized void a();
    descriptor: ()V
    Code:
       0: aload_0
       1: getfield      #21                 // Field a:Z
       4: ifeq          8
       7: return
       8: aload_0
       9: dup
      10: dup2
      11: new           #38                 // class com/adjust/sdk/sig/d
      14: dup
      15: invokespecial #207                // Method com/adjust/sdk/sig/d."<init>":()V
      18: putfield      #30                 // Field b:Lcom/adjust/sdk/sig/d;
      21: new           #62                 // class com/adjust/sdk/sig/c
      24: dup
      25: getstatic     #213                // Field android/os/Build$VERSION.SDK_INT:I
      28: invokespecial #216                // Method com/adjust/sdk/sig/c."<init>":(I)V
      31: putfield      #49                 // Field d:Lcom/adjust/sdk/sig/c;
      34: new           #43                 // class com/adjust/sdk/sig/NativeLibHelper
      37: dup
      38: invokespecial #217                // Method com/adjust/sdk/sig/NativeLibHelper."<init>":()V
      41: putfield      #32                 // Field c:Lcom/adjust/sdk/sig/a;
      44: iconst_1
      45: putfield      #21                 // Field a:Z
      48: return
}
Compiled from "SourceFile"
public final class com.adjust.sdk.sig.c {
  public final int a;
    descriptor: I

  public com.adjust.sdk.sig.c(int);
    descriptor: (I)V
    Code:
       0: aload_0
       1: dup
       2: invokespecial #14                 // Method java/lang/Object."<init>":()V
       5: iload_1
       6: putfield      #16                 // Field a:I
       9: return

  public final void a(android.content.Context);
    descriptor: (Landroid/content/Context;)V
    Code:
       0: aload_0
       1: getfield      #16                 // Field a:I
       4: dup
       5: istore_2
       6: bipush        23
       8: if_icmplt     63
      11: ldc           #19                 // String AndroidKeyStore
      13: invokestatic  #25                 // Method java/security/KeyStore.getInstance:(Ljava/lang/String;)Ljava/security/KeyStore;
      16: dup
      17: aconst_null
      18: invokevirtual #29                 // Method java/security/KeyStore.load:(Ljava/security/KeyStore$LoadStoreParameter;)V
      21: ldc           #31                 // String key2
      23: invokevirtual #35                 // Method java/security/KeyStore.containsAlias:(Ljava/lang/String;)Z
      26: ifeq          32
      29: goto          272
      32: ldc           #37                 // String HmacSHA256
      34: ldc           #19                 // String AndroidKeyStore
      36: invokestatic  #42                 // Method javax/crypto/KeyGenerator.getInstance:(Ljava/lang/String;Ljava/lang/String;)Ljavax/crypto/KeyGenerator;
      39: dup
      40: new           #44                 // class android/security/keystore/KeyGenParameterSpec$Builder
      43: dup
      44: ldc           #31                 // String key2
      46: iconst_4
      47: invokespecial #47                 // Method android/security/keystore/KeyGenParameterSpec$Builder."<init>":(Ljava/lang/String;I)V
      50: invokevirtual #51                 // Method android/security/keystore/KeyGenParameterSpec$Builder.build:()Landroid/security/keystore/KeyGenParameterSpec;
      53: invokevirtual #55                 // Method javax/crypto/KeyGenerator.init:(Ljava/security/spec/AlgorithmParameterSpec;)V
      56: invokevirtual #59                 // Method javax/crypto/KeyGenerator.generateKey:()Ljavax/crypto/SecretKey;
      59: pop
      60: goto          272
      63: iload_2
      64: bipush        18
      66: if_icmplt     273
      69: aload_1
      70: ldc           #63                 // String adjust_keys
      72: iconst_0
      73: invokevirtual #67                 // Method android/content/Context.getSharedPreferences:(Ljava/lang/String;I)Landroid/content/SharedPreferences;
      76: dup
      77: astore_2
      78: ldc           #69                 // String encrypted_key
      80: invokeinterface #74,  2           // InterfaceMethod android/content/SharedPreferences.contains:(Ljava/lang/String;)Z
      85: ifeq          91
      88: goto          272
      91: aload_0
      92: invokestatic  #79                 // Method java/util/Calendar.getInstance:()Ljava/util/Calendar;
      95: invokevirtual #83                 // Method java/util/Calendar.getTime:()Ljava/util/Date;
      98: astore_0
      99: invokestatic  #79                 // Method java/util/Calendar.getInstance:()Ljava/util/Calendar;
     102: dup
     103: iconst_1
     104: iconst_1
     105: invokevirtual #87                 // Method java/util/Calendar.add:(II)V
     108: invokevirtual #83                 // Method java/util/Calendar.getTime:()Ljava/util/Date;
     111: new           #89                 // class android/security/KeyPairGeneratorSpec$Builder
     114: dup
     115: aload_1
     116: invokespecial #91                 // Method android/security/KeyPairGeneratorSpec$Builder."<init>":(Landroid/content/Context;)V
     119: ldc           #31                 // String key2
     121: invokevirtual #95                 // Method android/security/KeyPairGeneratorSpec$Builder.setAlias:(Ljava/lang/String;)Landroid/security/KeyPairGeneratorSpec$Builder;
     124: new           #97                 // class javax/security/auth/x500/X500Principal
     127: dup
     128: ldc           #99                 // String CN=key2
     130: invokespecial #102                // Method javax/security/auth/x500/X500Principal."<init>":(Ljava/lang/String;)V
     133: invokevirtual #106                // Method android/security/KeyPairGeneratorSpec$Builder.setSubject:(Ljavax/security/auth/x500/X500Principal;)Landroid/security/KeyPairGeneratorSpec$Builder;
     136: getstatic     #112                // Field java/math/BigInteger.TEN:Ljava/math/BigInteger;
     139: invokevirtual #116                // Method android/security/KeyPairGeneratorSpec$Builder.setSerialNumber:(Ljava/math/BigInteger;)Landroid/security/KeyPairGeneratorSpec$Builder;
     142: aload_0
     143: invokevirtual #120                // Method android/security/KeyPairGeneratorSpec$Builder.setStartDate:(Ljava/util/Date;)Landroid/security/KeyPairGeneratorSpec$Builder;
     146: swap
     147: invokevirtual #123                // Method android/security/KeyPairGeneratorSpec$Builder.setEndDate:(Ljava/util/Date;)Landroid/security/KeyPairGeneratorSpec$Builder;
     150: astore_0
     151: getfield      #16                 // Field a:I
     154: bipush        19
     156: if_icmplt     167
     159: aload_0
     160: sipush        1024
     163: invokevirtual #127                // Method android/security/KeyPairGeneratorSpec$Builder.setKeySize:(I)Landroid/security/KeyPairGeneratorSpec$Builder;
     166: pop
     167: aload_2
     168: ldc           #129                // String RSA
     170: ldc           #19                 // String AndroidKeyStore
     172: invokestatic  #134                // Method java/security/KeyPairGenerator.getInstance:(Ljava/lang/String;Ljava/lang/String;)Ljava/security/KeyPairGenerator;
     175: dup
     176: aload_0
     177: invokevirtual #137                // Method android/security/KeyPairGeneratorSpec$Builder.build:()Landroid/security/KeyPairGeneratorSpec;
     180: invokevirtual #140                // Method java/security/KeyPairGenerator.initialize:(Ljava/security/spec/AlgorithmParameterSpec;)V
     183: invokevirtual #144                // Method java/security/KeyPairGenerator.genKeyPair:()Ljava/security/KeyPair;
     186: pop
     187: bipush        16
     189: newarray       byte
     191: astore_0
     192: new           #146                // class java/security/SecureRandom
     195: dup
     196: aload_0
     197: swap
     198: invokespecial #147                // Method java/security/SecureRandom."<init>":()V
     201: invokevirtual #151                // Method java/security/SecureRandom.nextBytes:([B)V
     204: ldc           #19                 // String AndroidKeyStore
     206: invokestatic  #25                 // Method java/security/KeyStore.getInstance:(Ljava/lang/String;)Ljava/security/KeyStore;
     209: dup
     210: aconst_null
     211: invokevirtual #29                 // Method java/security/KeyStore.load:(Ljava/security/KeyStore$LoadStoreParameter;)V
     214: ldc           #31                 // String key2
     216: aconst_null
     217: invokevirtual #155                // Method java/security/KeyStore.getEntry:(Ljava/lang/String;Ljava/security/KeyStore$ProtectionParameter;)Ljava/security/KeyStore$Entry;
     220: checkcast     #157                // class java/security/KeyStore$PrivateKeyEntry
     223: astore_1
     224: ldc           #159                // String RSA/ECB/PKCS1Padding
     226: invokestatic  #164                // Method javax/crypto/Cipher.getInstance:(Ljava/lang/String;)Ljavax/crypto/Cipher;
     229: dup
     230: aload_0
     231: swap
     232: aload_1
     233: invokevirtual #168                // Method java/security/KeyStore$PrivateKeyEntry.getCertificate:()Ljava/security/cert/Certificate;
     236: invokevirtual #174                // Method java/security/cert/Certificate.getPublicKey:()Ljava/security/PublicKey;
     239: iconst_1
     240: swap
     241: invokevirtual #177                // Method javax/crypto/Cipher.init:(ILjava/security/Key;)V
     244: invokevirtual #181                // Method javax/crypto/Cipher.doFinal:([B)[B
     247: iconst_0
     248: invokestatic  #187                // Method android/util/Base64.encodeToString:([BI)Ljava/lang/String;
     251: astore_0
     252: invokeinterface #191,  1          // InterfaceMethod android/content/SharedPreferences.edit:()Landroid/content/SharedPreferences$Editor;
     257: dup
     258: ldc           #69                 // String encrypted_key
     260: aload_0
     261: invokeinterface #197,  3          // InterfaceMethod android/content/SharedPreferences$Editor.putString:(Ljava/lang/String;Ljava/lang/String;)Landroid/content/SharedPreferences$Editor;
     266: pop
     267: invokeinterface #200,  1          // InterfaceMethod android/content/SharedPreferences$Editor.apply:()V
     272: return
     273: new           #202                // class com/adjust/sdk/sig/b
     276: dup
     277: invokespecial #203                // Method com/adjust/sdk/sig/b."<init>":()V
     280: athrow

  public final byte[] a(android.content.Context, byte[]);
    descriptor: (Landroid/content/Context;[B)[B
    Code:
       0: aload_0
       1: ldc           #37                 // String HmacSHA256
       3: invokestatic  #209                // Method javax/crypto/Mac.getInstance:(Ljava/lang/String;)Ljavax/crypto/Mac;
       6: astore_0
       7: getfield      #16                 // Field a:I
      10: dup
      11: istore_3
      12: bipush        23
      14: if_icmplt     37
      17: ldc           #19                 // String AndroidKeyStore
      19: invokestatic  #25                 // Method java/security/KeyStore.getInstance:(Ljava/lang/String;)Ljava/security/KeyStore;
      22: dup
      23: aconst_null
      24: invokevirtual #29                 // Method java/security/KeyStore.load:(Ljava/security/KeyStore$LoadStoreParameter;)V
      27: ldc           #31                 // String key2
      29: aconst_null
      30: invokevirtual #213                // Method java/security/KeyStore.getKey:(Ljava/lang/String;[C)Ljava/security/Key;
      33: astore_1
      34: goto          123
      37: iload_3
      38: bipush        18
      40: if_icmplt     148
      43: aload_1
      44: ldc           #63                 // String adjust_keys
      46: iconst_0
      47: invokevirtual #67                 // Method android/content/Context.getSharedPreferences:(Ljava/lang/String;I)Landroid/content/SharedPreferences;
      50: ldc           #69                 // String encrypted_key
      52: aconst_null
      53: invokeinterface #219,  3          // InterfaceMethod android/content/SharedPreferences.getString:(Ljava/lang/String;Ljava/lang/String;)Ljava/lang/String;
      58: dup
      59: astore_1
      60: ifnull        138
      63: aload_1
      64: iconst_0
      65: invokestatic  #223                // Method android/util/Base64.decode:(Ljava/lang/String;I)[B
      68: astore_1
      69: ldc           #19                 // String AndroidKeyStore
      71: invokestatic  #25                 // Method java/security/KeyStore.getInstance:(Ljava/lang/String;)Ljava/security/KeyStore;
      74: dup
      75: aconst_null
      76: invokevirtual #29                 // Method java/security/KeyStore.load:(Ljava/security/KeyStore$LoadStoreParameter;)V
      79: ldc           #31                 // String key2
      81: aconst_null
      82: invokevirtual #155                // Method java/security/KeyStore.getEntry:(Ljava/lang/String;Ljava/security/KeyStore$ProtectionParameter;)Ljava/security/KeyStore$Entry;
      85: checkcast     #157                // class java/security/KeyStore$PrivateKeyEntry
      88: astore_3
      89: ldc           #159                // String RSA/ECB/PKCS1Padding
      91: invokestatic  #164                // Method javax/crypto/Cipher.getInstance:(Ljava/lang/String;)Ljavax/crypto/Cipher;
      94: dup
      95: aload_1
      96: swap
      97: aload_3
      98: invokevirtual #227                // Method java/security/KeyStore$PrivateKeyEntry.getPrivateKey:()Ljava/security/PrivateKey;
     101: iconst_2
     102: swap
     103: invokevirtual #177                // Method javax/crypto/Cipher.init:(ILjava/security/Key;)V
     106: invokevirtual #181                // Method javax/crypto/Cipher.doFinal:([B)[B
     109: astore_1
     110: new           #229                // class javax/crypto/spec/SecretKeySpec
     113: dup
     114: astore_3
     115: aload_1
     116: ldc           #231                // String AES
     118: invokespecial #234                // Method javax/crypto/spec/SecretKeySpec."<init>":([BLjava/lang/String;)V
     121: aload_3
     122: astore_1
     123: aload_0
     124: dup
     125: aload_2
     126: aload_0
     127: aload_1
     128: invokevirtual #237                // Method javax/crypto/Mac.init:(Ljava/security/Key;)V
     131: invokevirtual #240                // Method javax/crypto/Mac.update:([B)V
     134: invokevirtual #243                // Method javax/crypto/Mac.doFinal:()[B
     137: areturn
     138: new           #245                // class java/lang/RuntimeException
     141: dup
     142: ldc           #247                // String Failed to find encrypted key in SharedPreferences
     144: invokespecial #248                // Method java/lang/RuntimeException."<init>":(Ljava/lang/String;)V
     147: athrow
     148: new           #245                // class java/lang/RuntimeException
     151: dup
     152: ldc           #250                // String Unsupported version
     154: invokespecial #248                // Method java/lang/RuntimeException."<init>":(Ljava/lang/String;)V
     157: athrow
}
Compiled from "SourceFile"
public final class com.adjust.sdk.sig.d {
  public static boolean a;
    descriptor: Z

  public com.adjust.sdk.sig.d();
    descriptor: ()V
    Code:
       0: aload_0
       1: invokespecial #14                 // Method java/lang/Object."<init>":()V
       4: return

  public static void a(android.content.Context, com.adjust.sdk.sig.c, com.adjust.sdk.sig.a, java.util.Map, java.lang.String, java.lang.String);
    descriptor: (Landroid/content/Context;Lcom/adjust/sdk/sig/c;Lcom/adjust/sdk/sig/a;Ljava/util/Map;Ljava/lang/String;Ljava/lang/String;)V
    Code:
       0: getstatic     #17                 // Field a:Z
       3: ifeq          15
       6: ldc           #19                 // String SignerInstance
       8: ldc           #21                 // String sign: library received error. It has locked down
      10: invokestatic  #27                 // Method android/util/Log.e:(Ljava/lang/String;Ljava/lang/String;)I
      13: pop
      14: return
      15: aload_3
      16: ifnull        615
      19: aload_3
      20: invokeinterface #33,  1           // InterfaceMethod java/util/Map.isEmpty:()Z
      25: ifne          615
      28: aload         4
      30: ifnull        615
      33: aload         5
      35: ifnonnull     41
      38: goto          615
      41: aload_3
      42: new           #35                 // class java/text/SimpleDateFormat
      45: dup
      46: astore        6
      48: getstatic     #41                 // Field java/util/Locale.US:Ljava/util/Locale;
      51: ldc           #43                 // String yyyy-MM-dd\'T\'HH:mm:ss.SSSZ
      53: swap
      54: invokespecial #46                 // Method java/text/SimpleDateFormat."<init>":(Ljava/lang/String;Ljava/util/Locale;)V
      57: ldc           #48                 // String environment
      59: invokeinterface #52,  2           // InterfaceMethod java/util/Map.get:(Ljava/lang/Object;)Ljava/lang/Object;
      64: ldc           #54                 // String sandbox
      66: swap
      67: invokevirtual #60                 // Method java/lang/String.equals:(Ljava/lang/Object;)Z
      70: dup
      71: istore        7
      73: ifeq          114
      76: new           #62                 // class java/lang/StringBuilder
      79: dup
      80: aload         6
      82: swap
      83: ldc           #64                 // String Signing all the parameters begin:
      85: invokespecial #67                 // Method java/lang/StringBuilder."<init>":(Ljava/lang/String;)V
      88: new           #69                 // class java/util/Date
      91: dup
      92: invokestatic  #75                 // Method java/lang/System.currentTimeMillis:()J
      95: invokespecial #78                 // Method java/util/Date."<init>":(J)V
      98: invokevirtual #84                 // Method java/text/DateFormat.format:(Ljava/util/Date;)Ljava/lang/String;
     101: invokevirtual #88                 // Method java/lang/StringBuilder.append:(Ljava/lang/String;)Ljava/lang/StringBuilder;
     104: invokevirtual #92                 // Method java/lang/StringBuilder.toString:()Ljava/lang/String;
     107: ldc           #19                 // String SignerInstance
     109: swap
     110: invokestatic  #95                 // Method android/util/Log.v:(Ljava/lang/String;Ljava/lang/String;)I
     113: pop
     114: aload_3
     115: dup
     116: ldc           #97                 // String activity_kind
     118: aload         4
     120: invokeinterface #101,  3          // InterfaceMethod java/util/Map.put:(Ljava/lang/Object;Ljava/lang/Object;)Ljava/lang/Object;
     125: pop
     126: ldc           #103                // String client_sdk
     128: aload         5
     130: invokeinterface #101,  3          // InterfaceMethod java/util/Map.put:(Ljava/lang/Object;Ljava/lang/Object;)Ljava/lang/Object;
     135: pop
     136: iconst_2
     137: istore        4
     139: aconst_null
     140: astore        5
     142: iload         4
     144: ifle          375
     147: aload_1
     148: aload_0
     149: aload_3
     150: aload_1
     151: aload_0
     152: invokevirtual #114                // Method com/adjust/sdk/sig/c.a:(Landroid/content/Context;)V
     155: invokevirtual #115                // Method java/lang/Object.toString:()Ljava/lang/String;
     158: getstatic     #121                // Field java/nio/charset/StandardCharsets.UTF_8:Ljava/nio/charset/Charset;
     161: invokevirtual #125                // Method java/lang/String.getBytes:(Ljava/nio/charset/Charset;)[B
     164: invokevirtual #128                // Method com/adjust/sdk/sig/c.a:(Landroid/content/Context;[B)[B
     167: astore        5
     169: goto          375
     172: astore_0
     173: goto          190
     176: astore        8
     178: goto          238
     181: astore        8
     183: goto          238
     186: astore_0
     187: goto          343
     190: aload_0
     191: aload_3
     192: dup
     193: new           #62                 // class java/lang/StringBuilder
     196: dup
     197: aload_0
     198: swap
     199: ldc           #138                // String sign: Received an Exception:
     201: invokespecial #67                 // Method java/lang/StringBuilder."<init>":(Ljava/lang/String;)V
     204: invokevirtual #143                // Method java/lang/Throwable.getMessage:()Ljava/lang/String;
     207: invokevirtual #88                 // Method java/lang/StringBuilder.append:(Ljava/lang/String;)Ljava/lang/StringBuilder;
     210: invokevirtual #92                 // Method java/lang/StringBuilder.toString:()Ljava/lang/String;
     213: ldc           #19                 // String SignerInstance
     215: swap
     216: aload_0
     217: invokestatic  #146                // Method android/util/Log.e:(Ljava/lang/String;Ljava/lang/String;Ljava/lang/Throwable;)I
     220: pop
     221: ldc           #97                 // String activity_kind
     223: invokeinterface #149,  2          // InterfaceMethod java/util/Map.remove:(Ljava/lang/Object;)Ljava/lang/Object;
     228: pop
     229: ldc           #103                // String client_sdk
     231: invokeinterface #149,  2          // InterfaceMethod java/util/Map.remove:(Ljava/lang/Object;)Ljava/lang/Object;
     236: pop
     237: athrow
     238: aload_0
     239: aload_1
     240: new           #62                 // class java/lang/StringBuilder
     243: dup
     244: aload         8
     246: swap
     247: ldc           #153                // String sign: Received a retriable exception:
     249: invokespecial #67                 // Method java/lang/StringBuilder."<init>":(Ljava/lang/String;)V
     252: invokevirtual #143                // Method java/lang/Throwable.getMessage:()Ljava/lang/String;
     255: invokevirtual #88                 // Method java/lang/StringBuilder.append:(Ljava/lang/String;)Ljava/lang/StringBuilder;
     258: invokevirtual #92                 // Method java/lang/StringBuilder.toString:()Ljava/lang/String;
     261: ldc           #19                 // String SignerInstance
     263: swap
     264: aload         8
     266: invokestatic  #146                // Method android/util/Log.e:(Ljava/lang/String;Ljava/lang/String;Ljava/lang/Throwable;)I
     269: pop
     270: new           #62                 // class java/lang/StringBuilder
     273: dup
     274: iload         4
     276: swap
     277: ldc           #155                // String sign: Attempting retry #
     279: invokespecial #67                 // Method java/lang/StringBuilder."<init>":(Ljava/lang/String;)V
     282: invokevirtual #158                // Method java/lang/StringBuilder.append:(I)Ljava/lang/StringBuilder;
     285: invokevirtual #92                 // Method java/lang/StringBuilder.toString:()Ljava/lang/String;
     288: ldc           #19                 // String SignerInstance
     290: swap
     291: invokestatic  #27                 // Method android/util/Log.e:(Ljava/lang/String;Ljava/lang/String;)I
     294: pop
     295: iinc          4, -1
     298: invokevirtual #162                // Method java/lang/Object.getClass:()Ljava/lang/Class;
     301: pop
     302: ldc           #164                // String AndroidKeyStore
     304: invokestatic  #170                // Method java/security/KeyStore.getInstance:(Ljava/lang/String;)Ljava/security/KeyStore;
     307: dup
     308: aconst_null
     309: invokevirtual #174                // Method java/security/KeyStore.load:(Ljava/security/KeyStore$LoadStoreParameter;)V
     312: ldc           #176                // String key2
     314: invokevirtual #179                // Method java/security/KeyStore.deleteEntry:(Ljava/lang/String;)V
     317: ldc           #181                // String adjust_keys
     319: iconst_0
     320: invokevirtual #185                // Method android/content/Context.getSharedPreferences:(Ljava/lang/String;I)Landroid/content/SharedPreferences;
     323: invokeinterface #191,  1          // InterfaceMethod android/content/SharedPreferences.edit:()Landroid/content/SharedPreferences$Editor;
     328: ldc           #193                // String encrypted_key
     330: invokeinterface #198,  2          // InterfaceMethod android/content/SharedPreferences$Editor.remove:(Ljava/lang/String;)Landroid/content/SharedPreferences$Editor;
     335: invokeinterface #201,  1          // InterfaceMethod android/content/SharedPreferences$Editor.apply:()V
     340: goto          142
     343: aload_0
     344: aload_3
     345: dup
     346: ldc           #19                 // String SignerInstance
     348: ldc           #203                // String sign: Api is less than JellyBean-4-18
     350: invokestatic  #27                 // Method android/util/Log.e:(Ljava/lang/String;Ljava/lang/String;)I
     353: pop
     354: iconst_1
     355: putstatic     #17                 // Field a:Z
     358: ldc           #97                 // String activity_kind
     360: invokeinterface #149,  2          // InterfaceMethod java/util/Map.remove:(Ljava/lang/Object;)Ljava/lang/Object;
     365: pop
     366: ldc           #103                // String client_sdk
     368: invokeinterface #149,  2          // InterfaceMethod java/util/Map.remove:(Ljava/lang/Object;)Ljava/lang/Object;
     373: pop
     374: athrow
     375: iload         4
     377: ifne          403
     380: aload_3
     381: dup
     382: iconst_1
     383: putstatic     #17                 // Field a:Z
     386: ldc           #97                 // String activity_kind
     388: invokeinterface #149,  2          // InterfaceMethod java/util/Map.remove:(Ljava/lang/Object;)Ljava/lang/Object;
     393: pop
     394: ldc           #103                // String client_sdk
     396: invokeinterface #149,  2          // InterfaceMethod java/util/Map.remove:(Ljava/lang/Object;)Ljava/lang/Object;
     401: pop
     402: return
     403: iload         7
     405: ifeq          446
     408: new           #62                 // class java/lang/StringBuilder
     411: dup
     412: aload         6
     414: swap
     415: ldc           #205                // String Calling native begin:
     417: invokespecial #67                 // Method java/lang/StringBuilder."<init>":(Ljava/lang/String;)V
     420: new           #69                 // class java/util/Date
     423: dup
     424: invokestatic  #75                 // Method java/lang/System.currentTimeMillis:()J
     427: invokespecial #78                 // Method java/util/Date."<init>":(J)V
     430: invokevirtual #84                 // Method java/text/DateFormat.format:(Ljava/util/Date;)Ljava/lang/String;
     433: invokevirtual #88                 // Method java/lang/StringBuilder.append:(Ljava/lang/String;)Ljava/lang/StringBuilder;
     436: invokevirtual #92                 // Method java/lang/StringBuilder.toString:()Ljava/lang/String;
     439: ldc           #19                 // String SignerInstance
     441: swap
     442: invokestatic  #95                 // Method android/util/Log.v:(Ljava/lang/String;Ljava/lang/String;)I
     445: pop
     446: iload         7
     448: aload_2
     449: aload_1
     450: getfield      #208                // Field com/adjust/sdk/sig/c.a:I
     453: istore_1
     454: checkcast     #210                // class com/adjust/sdk/sig/NativeLibHelper
     457: aload_0
     458: aload_3
     459: aload         5
     461: iload_1
     462: invokevirtual #213                // Method com/adjust/sdk/sig/NativeLibHelper.a:(Landroid/content/Context;Ljava/lang/Object;[BI)[B
     465: astore_0
     466: ifeq          507
     469: new           #62                 // class java/lang/StringBuilder
     472: dup
     473: aload         6
     475: swap
     476: ldc           #215                // String Calling native end  :
     478: invokespecial #67                 // Method java/lang/StringBuilder."<init>":(Ljava/lang/String;)V
     481: new           #69                 // class java/util/Date
     484: dup
     485: invokestatic  #75                 // Method java/lang/System.currentTimeMillis:()J
     488: invokespecial #78                 // Method java/util/Date."<init>":(J)V
     491: invokevirtual #84                 // Method java/text/DateFormat.format:(Ljava/util/Date;)Ljava/lang/String;
     494: invokevirtual #88                 // Method java/lang/StringBuilder.append:(Ljava/lang/String;)Ljava/lang/StringBuilder;
     497: invokevirtual #92                 // Method java/lang/StringBuilder.toString:()Ljava/lang/String;
     500: ldc           #19                 // String SignerInstance
     502: swap
     503: invokestatic  #95                 // Method android/util/Log.v:(Ljava/lang/String;Ljava/lang/String;)I
     506: pop
     507: aload_0
     508: ifnonnull     538
     511: aload_3
     512: dup
     513: ldc           #19                 // String SignerInstance
     515: ldc           #217                // String sign: Returned an null signature. Exiting...
     517: invokestatic  #27                 // Method android/util/Log.e:(Ljava/lang/String;Ljava/lang/String;)I
     520: pop
     521: ldc           #97                 // String activity_kind
     523: invokeinterface #149,  2          // InterfaceMethod java/util/Map.remove:(Ljava/lang/Object;)Ljava/lang/Object;
     528: pop
     529: ldc           #103                // String client_sdk
     531: invokeinterface #149,  2          // InterfaceMethod java/util/Map.remove:(Ljava/lang/Object;)Ljava/lang/Object;
     536: pop
     537: return
     538: iload         7
     540: aload_3
     541: dup
     542: dup
     543: aload_0
     544: iconst_2
     545: invokestatic  #223                // Method android/util/Base64.encodeToString:([BI)Ljava/lang/String;
     548: ldc           #225                // String signature
     550: swap
     551: invokeinterface #101,  3          // InterfaceMethod java/util/Map.put:(Ljava/lang/Object;Ljava/lang/Object;)Ljava/lang/Object;
     556: pop
     557: ldc           #97                 // String activity_kind
     559: invokeinterface #149,  2          // InterfaceMethod java/util/Map.remove:(Ljava/lang/Object;)Ljava/lang/Object;
     564: pop
     565: ldc           #103                // String client_sdk
     567: invokeinterface #149,  2          // InterfaceMethod java/util/Map.remove:(Ljava/lang/Object;)Ljava/lang/Object;
     572: pop
     573: ifeq          614
     576: new           #62                 // class java/lang/StringBuilder
     579: dup
     580: aload         6
     582: swap
     583: ldc           #227                // String Signing all the parameters end  :
     585: invokespecial #67                 // Method java/lang/StringBuilder."<init>":(Ljava/lang/String;)V
     588: new           #69                 // class java/util/Date
     591: dup
     592: invokestatic  #75                 // Method java/lang/System.currentTimeMillis:()J
     595: invokespecial #78                 // Method java/util/Date."<init>":(J)V
     598: invokevirtual #84                 // Method java/text/DateFormat.format:(Ljava/util/Date;)Ljava/lang/String;
     601: invokevirtual #88                 // Method java/lang/StringBuilder.append:(Ljava/lang/String;)Ljava/lang/StringBuilder;
     604: invokevirtual #92                 // Method java/lang/StringBuilder.toString:()Ljava/lang/String;
     607: ldc           #19                 // String SignerInstance
     609: swap
     610: invokestatic  #95                 // Method android/util/Log.v:(Ljava/lang/String;Ljava/lang/String;)I
     613: pop
     614: return
     615: ldc           #19                 // String SignerInstance
     617: ldc           #229                // String sign: One or more parameters are null
     619: invokestatic  #27                 // Method android/util/Log.e:(Ljava/lang/String;Ljava/lang/String;)I
     622: pop
     623: return
    Exception table:
       from    to  target type
         147   167   186   Class com/adjust/sdk/sig/b
         147   167   181   Class java/security/UnrecoverableKeyException
         147   167   176   Class java/security/InvalidKeyException
         147   167   172   Class java/lang/Exception

  public static void a(java.util.Set, java.util.Map, java.util.Map);
    descriptor: (Ljava/util/Set;Ljava/util/Map;Ljava/util/Map;)V
    Code:
       0: aload_0
       1: invokeinterface #236,  1          // InterfaceMethod java/util/Set.iterator:()Ljava/util/Iterator;
       6: astore_0
       7: aload_0
       8: invokeinterface #241,  1          // InterfaceMethod java/util/Iterator.hasNext:()Z
      13: ifeq          57
      16: aload_1
      17: aload_0
      18: invokeinterface #245,  1          // InterfaceMethod java/util/Iterator.next:()Ljava/lang/Object;
      23: checkcast     #56                 // class java/lang/String
      26: dup
      27: astore_3
      28: invokeinterface #248,  2          // InterfaceMethod java/util/Map.containsKey:(Ljava/lang/Object;)Z
      33: ifeq          7
      36: aload_2
      37: aload_3
      38: aload_1
      39: aload_3
      40: invokeinterface #52,  2           // InterfaceMethod java/util/Map.get:(Ljava/lang/Object;)Ljava/lang/Object;
      45: checkcast     #56                 // class java/lang/String
      48: invokeinterface #101,  3          // InterfaceMethod java/util/Map.put:(Ljava/lang/Object;Ljava/lang/Object;)Ljava/lang/Object;
      53: pop
      54: goto          7
      57: return
}
