Compiled from "SourceFile"
public final class com.adjust.sdk.sig.c {
  public final int a;
    descriptor: I

  public com.adjust.sdk.sig.c(int);
    descriptor: (I)V
    Code:
       0: aload_0
       1: dup
       2: invokespecial #14                 // Method java/lang/Object."<init>":()V
       5: iload_1
       6: putfield      #16                 // Field a:I
       9: return

  public final void a(android.content.Context);
    descriptor: (Landroid/content/Context;)V
    Code:
       0: aload_0
       1: getfield      #16                 // Field a:I
       4: dup
       5: istore_2
       6: bipush        23
       8: if_icmplt     63
      11: ldc           #19                 // String AndroidKeyStore
      13: invokestatic  #25                 // Method java/security/KeyStore.getInstance:(Ljava/lang/String;)Ljava/security/KeyStore;
      16: dup
      17: aconst_null
      18: invokevirtual #29                 // Method java/security/KeyStore.load:(Ljava/security/KeyStore$LoadStoreParameter;)V
      21: ldc           #31                 // String key2
      23: invokevirtual #35                 // Method java/security/KeyStore.containsAlias:(Ljava/lang/String;)Z
      26: ifeq          32
      29: goto          272
      32: ldc           #37                 // String HmacSHA256
      34: ldc           #19                 // String AndroidKeyStore
      36: invokestatic  #42                 // Method javax/crypto/KeyGenerator.getInstance:(Ljava/lang/String;Ljava/lang/String;)Ljavax/crypto/KeyGenerator;
      39: dup
      40: new           #44                 // class android/security/keystore/KeyGenParameterSpec$Builder
      43: dup
      44: ldc           #31                 // String key2
      46: iconst_4
      47: invokespecial #47                 // Method android/security/keystore/KeyGenParameterSpec$Builder."<init>":(Ljava/lang/String;I)V
      50: invokevirtual #51                 // Method android/security/keystore/KeyGenParameterSpec$Builder.build:()Landroid/security/keystore/KeyGenParameterSpec;
      53: invokevirtual #55                 // Method javax/crypto/KeyGenerator.init:(Ljava/security/spec/AlgorithmParameterSpec;)V
      56: invokevirtual #59                 // Method javax/crypto/KeyGenerator.generateKey:()Ljavax/crypto/SecretKey;
      59: pop
      60: goto          272
      63: iload_2
      64: bipush        18
      66: if_icmplt     273
      69: aload_1
      70: ldc           #63                 // String adjust_keys
      72: iconst_0
      73: invokevirtual #67                 // Method android/content/Context.getSharedPreferences:(Ljava/lang/String;I)Landroid/content/SharedPreferences;
      76: dup
      77: astore_2
      78: ldc           #69                 // String encrypted_key
      80: invokeinterface #74,  2           // InterfaceMethod android/content/SharedPreferences.contains:(Ljava/lang/String;)Z
      85: ifeq          91
      88: goto          272
      91: aload_0
      92: invokestatic  #79                 // Method java/util/Calendar.getInstance:()Ljava/util/Calendar;
      95: invokevirtual #83                 // Method java/util/Calendar.getTime:()Ljava/util/Date;
      98: astore_0
      99: invokestatic  #79                 // Method java/util/Calendar.getInstance:()Ljava/util/Calendar;
     102: dup
     103: iconst_1
     104: iconst_1
     105: invokevirtual #87                 // Method java/util/Calendar.add:(II)V
     108: invokevirtual #83                 // Method java/util/Calendar.getTime:()Ljava/util/Date;
     111: new           #89                 // class android/security/KeyPairGeneratorSpec$Builder
     114: dup
     115: aload_1
     116: invokespecial #91                 // Method android/security/KeyPairGeneratorSpec$Builder."<init>":(Landroid/content/Context;)V
     119: ldc           #31                 // String key2
     121: invokevirtual #95                 // Method android/security/KeyPairGeneratorSpec$Builder.setAlias:(Ljava/lang/String;)Landroid/security/KeyPairGeneratorSpec$Builder;
     124: new           #97                 // class javax/security/auth/x500/X500Principal
     127: dup
     128: ldc           #99                 // String CN=key2
     130: invokespecial #102                // Method javax/security/auth/x500/X500Principal."<init>":(Ljava/lang/String;)V
     133: invokevirtual #106                // Method android/security/KeyPairGeneratorSpec$Builder.setSubject:(Ljavax/security/auth/x500/X500Principal;)Landroid/security/KeyPairGeneratorSpec$Builder;
     136: getstatic     #112                // Field java/math/BigInteger.TEN:Ljava/math/BigInteger;
     139: invokevirtual #116                // Method android/security/KeyPairGeneratorSpec$Builder.setSerialNumber:(Ljava/math/BigInteger;)Landroid/security/KeyPairGeneratorSpec$Builder;
     142: aload_0
     143: invokevirtual #120                // Method android/security/KeyPairGeneratorSpec$Builder.setStartDate:(Ljava/util/Date;)Landroid/security/KeyPairGeneratorSpec$Builder;
     146: swap
     147: invokevirtual #123                // Method android/security/KeyPairGeneratorSpec$Builder.setEndDate:(Ljava/util/Date;)Landroid/security/KeyPairGeneratorSpec$Builder;
     150: astore_0
     151: getfield      #16                 // Field a:I
     154: bipush        19
     156: if_icmplt     167
     159: aload_0
     160: sipush        1024
     163: invokevirtual #127                // Method android/security/KeyPairGeneratorSpec$Builder.setKeySize:(I)Landroid/security/KeyPairGeneratorSpec$Builder;
     166: pop
     167: aload_2
     168: ldc           #129                // String RSA
     170: ldc           #19                 // String AndroidKeyStore
     172: invokestatic  #134                // Method java/security/KeyPairGenerator.getInstance:(Ljava/lang/String;Ljava/lang/String;)Ljava/security/KeyPairGenerator;
     175: dup
     176: aload_0
     177: invokevirtual #137                // Method android/security/KeyPairGeneratorSpec$Builder.build:()Landroid/security/KeyPairGeneratorSpec;
     180: invokevirtual #140                // Method java/security/KeyPairGenerator.initialize:(Ljava/security/spec/AlgorithmParameterSpec;)V
     183: invokevirtual #144                // Method java/security/KeyPairGenerator.genKeyPair:()Ljava/security/KeyPair;
     186: pop
     187: bipush        16
     189: newarray       byte
     191: astore_0
     192: new           #146                // class java/security/SecureRandom
     195: dup
     196: aload_0
     197: swap
     198: invokespecial #147                // Method java/security/SecureRandom."<init>":()V
     201: invokevirtual #151                // Method java/security/SecureRandom.nextBytes:([B)V
     204: ldc           #19                 // String AndroidKeyStore
     206: invokestatic  #25                 // Method java/security/KeyStore.getInstance:(Ljava/lang/String;)Ljava/security/KeyStore;
     209: dup
     210: aconst_null
     211: invokevirtual #29                 // Method java/security/KeyStore.load:(Ljava/security/KeyStore$LoadStoreParameter;)V
     214: ldc           #31                 // String key2
     216: aconst_null
     217: invokevirtual #155                // Method java/security/KeyStore.getEntry:(Ljava/lang/String;Ljava/security/KeyStore$ProtectionParameter;)Ljava/security/KeyStore$Entry;
     220: checkcast     #157                // class java/security/KeyStore$PrivateKeyEntry
     223: astore_1
     224: ldc           #159                // String RSA/ECB/PKCS1Padding
     226: invokestatic  #164                // Method javax/crypto/Cipher.getInstance:(Ljava/lang/String;)Ljavax/crypto/Cipher;
     229: dup
     230: aload_0
     231: swap
     232: aload_1
     233: invokevirtual #168                // Method java/security/KeyStore$PrivateKeyEntry.getCertificate:()Ljava/security/cert/Certificate;
     236: invokevirtual #174                // Method java/security/cert/Certificate.getPublicKey:()Ljava/security/PublicKey;
     239: iconst_1
     240: swap
     241: invokevirtual #177                // Method javax/crypto/Cipher.init:(ILjava/security/Key;)V
     244: invokevirtual #181                // Method javax/crypto/Cipher.doFinal:([B)[B
     247: iconst_0
     248: invokestatic  #187                // Method android/util/Base64.encodeToString:([BI)Ljava/lang/String;
     251: astore_0
     252: invokeinterface #191,  1          // InterfaceMethod android/content/SharedPreferences.edit:()Landroid/content/SharedPreferences$Editor;
     257: dup
     258: ldc           #69                 // String encrypted_key
     260: aload_0
     261: invokeinterface #197,  3          // InterfaceMethod android/content/SharedPreferences$Editor.putString:(Ljava/lang/String;Ljava/lang/String;)Landroid/content/SharedPreferences$Editor;
     266: pop
     267: invokeinterface #200,  1          // InterfaceMethod android/content/SharedPreferences$Editor.apply:()V
     272: return
     273: new           #202                // class com/adjust/sdk/sig/b
     276: dup
     277: invokespecial #203                // Method com/adjust/sdk/sig/b."<init>":()V
     280: athrow

  public final byte[] a(android.content.Context, byte[]);
    descriptor: (Landroid/content/Context;[B)[B
    Code:
       0: aload_0
       1: ldc           #37                 // String HmacSHA256
       3: invokestatic  #209                // Method javax/crypto/Mac.getInstance:(Ljava/lang/String;)Ljavax/crypto/Mac;
       6: astore_0
       7: getfield      #16                 // Field a:I
      10: dup
      11: istore_3
      12: bipush        23
      14: if_icmplt     37
      17: ldc           #19                 // String AndroidKeyStore
      19: invokestatic  #25                 // Method java/security/KeyStore.getInstance:(Ljava/lang/String;)Ljava/security/KeyStore;
      22: dup
      23: aconst_null
      24: invokevirtual #29                 // Method java/security/KeyStore.load:(Ljava/security/KeyStore$LoadStoreParameter;)V
      27: ldc           #31                 // String key2
      29: aconst_null
      30: invokevirtual #213                // Method java/security/KeyStore.getKey:(Ljava/lang/String;[C)Ljava/security/Key;
      33: astore_1
      34: goto          123
      37: iload_3
      38: bipush        18
      40: if_icmplt     148
      43: aload_1
      44: ldc           #63                 // String adjust_keys
      46: iconst_0
      47: invokevirtual #67                 // Method android/content/Context.getSharedPreferences:(Ljava/lang/String;I)Landroid/content/SharedPreferences;
      50: ldc           #69                 // String encrypted_key
      52: aconst_null
      53: invokeinterface #219,  3          // InterfaceMethod android/content/SharedPreferences.getString:(Ljava/lang/String;Ljava/lang/String;)Ljava/lang/String;
      58: dup
      59: astore_1
      60: ifnull        138
      63: aload_1
      64: iconst_0
      65: invokestatic  #223                // Method android/util/Base64.decode:(Ljava/lang/String;I)[B
      68: astore_1
      69: ldc           #19                 // String AndroidKeyStore
      71: invokestatic  #25                 // Method java/security/KeyStore.getInstance:(Ljava/lang/String;)Ljava/security/KeyStore;
      74: dup
      75: aconst_null
      76: invokevirtual #29                 // Method java/security/KeyStore.load:(Ljava/security/KeyStore$LoadStoreParameter;)V
      79: ldc           #31                 // String key2
      81: aconst_null
      82: invokevirtual #155                // Method java/security/KeyStore.getEntry:(Ljava/lang/String;Ljava/security/KeyStore$ProtectionParameter;)Ljava/security/KeyStore$Entry;
      85: checkcast     #157                // class java/security/KeyStore$PrivateKeyEntry
      88: astore_3
      89: ldc           #159                // String RSA/ECB/PKCS1Padding
      91: invokestatic  #164                // Method javax/crypto/Cipher.getInstance:(Ljava/lang/String;)Ljavax/crypto/Cipher;
      94: dup
      95: aload_1
      96: swap
      97: aload_3
      98: invokevirtual #227                // Method java/security/KeyStore$PrivateKeyEntry.getPrivateKey:()Ljava/security/PrivateKey;
     101: iconst_2
     102: swap
     103: invokevirtual #177                // Method javax/crypto/Cipher.init:(ILjava/security/Key;)V
     106: invokevirtual #181                // Method javax/crypto/Cipher.doFinal:([B)[B
     109: astore_1
     110: new           #229                // class javax/crypto/spec/SecretKeySpec
     113: dup
     114: astore_3
     115: aload_1
     116: ldc           #231                // String AES
     118: invokespecial #234                // Method javax/crypto/spec/SecretKeySpec."<init>":([BLjava/lang/String;)V
     121: aload_3
     122: astore_1
     123: aload_0
     124: dup
     125: aload_2
     126: aload_0
     127: aload_1
     128: invokevirtual #237                // Method javax/crypto/Mac.init:(Ljava/security/Key;)V
     131: invokevirtual #240                // Method javax/crypto/Mac.update:([B)V
     134: invokevirtual #243                // Method javax/crypto/Mac.doFinal:()[B
     137: areturn
     138: new           #245                // class java/lang/RuntimeException
     141: dup
     142: ldc           #247                // String Failed to find encrypted key in SharedPreferences
     144: invokespecial #248                // Method java/lang/RuntimeException."<init>":(Ljava/lang/String;)V
     147: athrow
     148: new           #245                // class java/lang/RuntimeException
     151: dup
     152: ldc           #250                // String Unsupported version
     154: invokespecial #248                // Method java/lang/RuntimeException."<init>":(Ljava/lang/String;)V
     157: athrow
}
